{"record":{"chromosome":"4","pos":130175090,"id":"essv19103978","reference":"T","alt":["DEL"],"quality":null,"filter":".","info":{"EXPERIMENT":{"EXPERIMENT":9},"DBVARID":"DBVARID","SVTYPE":{"SVTYPE":"DEL"},"REGION":{"REGION":"esv3837075"},"CALLID":{"CALLID":"DEL_pindel_13217_NA12878"},"END":{"END":130175155},"SAMPLE":{"SAMPLE":"NA12878"}}},"fa_location":"/mnt/disk1/felix/supporting_reads/NA12878/essv19103978.DEL.130175090-130175155.fa","sam_location":"/mnt/disk1/felix/supporting_reads/NA12878/essv19103978.DEL.130175090-130175155.sam"}