{"record":{"chromosome":"12","pos":240153,"id":"essv22639110","reference":"T","alt":["DEL"],"quality":null,"filter":".","info":{"SAMPLE":{"SAMPLE":"NA12878"},"REGION":{"REGION":"esv3866095"},"CALLID":{"CALLID":"DEL_pindel_35183_NA12878"},"EXPERIMENT":{"EXPERIMENT":9},"SVTYPE":{"SVTYPE":"DEL"},"END":{"END":240208},"DBVARID":"DBVARID"}},"fa_location":"/mnt/disk1/felix/supporting_reads/NA12878/essv22639110.DEL.240153-240208.fa","sam_location":"/mnt/disk1/felix/supporting_reads/NA12878/essv22639110.DEL.240153-240208.sam"}