{"record":{"chromosome":"5","pos":43523638,"id":"essv19476971","reference":"A","alt":["DEL"],"quality":null,"filter":".","info":{"CALLID":{"CALLID":"DEL_pindel_15337_NA12878"},"SVTYPE":{"SVTYPE":"DEL"},"EXPERIMENT":{"EXPERIMENT":9},"END":{"END":43523692},"DBVARID":"DBVARID","REGION":{"REGION":"esv3840114"},"SAMPLE":{"SAMPLE":"NA12878"}}},"fa_location":"/mnt/disk1/felix/supporting_reads/NA12878/essv19476971.DEL.43523638-43523692.fa","sam_location":"/mnt/disk1/felix/supporting_reads/NA12878/essv19476971.DEL.43523638-43523692.sam"}