{"record":{"chromosome":"3","pos":189995603,"id":"essv18651116","reference":"T","alt":["DEL"],"quality":null,"filter":".","info":{"SVTYPE":{"SVTYPE":"DEL"},"REGION":{"REGION":"esv3833527"},"EXPERIMENT":{"EXPERIMENT":9},"SAMPLE":{"SAMPLE":"NA12878"},"DBVARID":"DBVARID","END":{"END":189995669},"CALLID":{"CALLID":"DEL_pindel_10511_NA12878"}}},"fa_location":"/mnt/disk1/felix/supporting_reads/NA12878/essv18651116.DEL.189995603-189995669.fa","sam_location":"/mnt/disk1/felix/supporting_reads/NA12878/essv18651116.DEL.189995603-189995669.sam"}