{"record":{"chromosome":"11","pos":123230020,"id":"essv22599990","reference":"G","alt":["DEL"],"quality":null,"filter":".","info":{"REGION":{"REGION":"esv3865797"},"END":{"END":123230075},"SAMPLE":{"SAMPLE":"NA12878"},"EXPERIMENT":{"EXPERIMENT":9},"DBVARID":"DBVARID","CALLID":{"CALLID":"DEL_pindel_34926_NA12878"},"SVTYPE":{"SVTYPE":"DEL"}}},"fa_location":"/mnt/disk1/felix/supporting_reads/NA12878/essv22599990.DEL.123230020-123230075.fa","sam_location":"/mnt/disk1/felix/supporting_reads/NA12878/essv22599990.DEL.123230020-123230075.sam"}