{"record":{"chromosome":"15","pos":76884546,"id":"essv23811187","reference":"A","alt":["CNV"],"quality":null,"filter":".","info":{"SAMPLE":{"SAMPLE":"NA12878"},"CALLID":{"CALLID":"DUP_gs_CNV_15_76884546_76895794_NA12878"},"EXPERIMENT":{"EXPERIMENT":9},"DBVARID":"DBVARID","SVTYPE":{"SVTYPE":"CNV"},"END":{"END":76895794},"REGION":{"REGION":"esv3875644"}}},"fa_location":"/mnt/disk1/felix/supporting_reads/NA12878/essv23811187.CNV.76884546-76895794.fa","sam_location":"/mnt/disk1/felix/supporting_reads/NA12878/essv23811187.CNV.76884546-76895794.sam"}