{"record":{"chromosome":"7","pos":82910896,"id":"essv20748819","reference":"T","alt":["DEL"],"quality":null,"filter":".","info":{"EXPERIMENT":{"EXPERIMENT":9},"SVTYPE":{"SVTYPE":"DEL"},"CALLID":{"CALLID":"DEL_pindel_23000_NA12878"},"END":{"END":82910958},"DBVARID":"DBVARID","SAMPLE":{"SAMPLE":"NA12878"},"REGION":{"REGION":"esv3850199"}}},"fa_location":"/mnt/disk1/felix/supporting_reads/NA12878/essv20748819.DEL.82910896-82910958.fa","sam_location":"/mnt/disk1/felix/supporting_reads/NA12878/essv20748819.DEL.82910896-82910958.sam"}