{"record":{"chromosome":"12","pos":115023766,"id":"essv22979013","reference":"C","alt":["DEL"],"quality":null,"filter":".","info":{"REGION":{"REGION":"esv3868952"},"EXPERIMENT":{"EXPERIMENT":9},"DBVARID":"DBVARID","SVTYPE":{"SVTYPE":"DEL"},"SAMPLE":{"SAMPLE":"NA12878"},"END":{"END":115023828},"CALLID":{"CALLID":"DEL_pindel_37371_NA12878"}}},"fa_location":"/mnt/disk1/felix/supporting_reads/NA12878/essv22979013.DEL.115023766-115023828.fa","sam_location":"/mnt/disk1/felix/supporting_reads/NA12878/essv22979013.DEL.115023766-115023828.sam"}