{"record":{"chromosome":"3","pos":45831052,"id":"essv18283399","reference":"C","alt":["DEL"],"quality":null,"filter":".","info":{"REGION":{"REGION":"esv3830157"},"SAMPLE":{"SAMPLE":"NA12878"},"CALLID":{"CALLID":"DEL_pindel_7904_NA12878"},"DBVARID":"DBVARID","END":{"END":45831105},"SVTYPE":{"SVTYPE":"DEL"},"EXPERIMENT":{"EXPERIMENT":9}}},"fa_location":"/mnt/disk1/felix/supporting_reads/NA12878/essv18283399.DEL.45831052-45831105.fa","sam_location":"/mnt/disk1/felix/supporting_reads/NA12878/essv18283399.DEL.45831052-45831105.sam"}