{"record":{"chromosome":"X","pos":76881497,"id":"essv25414822","reference":"A","alt":["DEL"],"quality":null,"filter":".","info":{"SAMPLE":{"SAMPLE":"NA12878"},"EXPERIMENT":{"EXPERIMENT":9},"CALLID":{"CALLID":"DEL_pindel_53951_NA12878"},"SVTYPE":{"SVTYPE":"DEL"},"REGION":{"REGION":"esv3889283"},"END":{"END":76881558},"DBVARID":"DBVARID"}},"fa_location":"/mnt/disk1/felix/supporting_reads/NA12878/essv25414822.DEL.76881497-76881558.fa","sam_location":"/mnt/disk1/felix/supporting_reads/NA12878/essv25414822.DEL.76881497-76881558.sam"}